[
    {
        "fileName": "147-CJL47.xlsx",
        "fileUrl": "https://docs.google.com/spreadsheets/d/10e350aNBCYERfx4IzecaC3dQF6y6VDsJ/edit?usp=drivesdk&ouid=107324667091065556014&rtpof=true&sd=true",
        "course": "47",
        "semester": "HK2",
        "year": "2025-2026"
    },
    {
        "fileName": "146-AUF47.xlsx",
        "fileUrl": "https://docs.google.com/spreadsheets/d/1FJEWxMPBU-egajU61PZK_9tJWClmckcb/edit?usp=drivesdk&ouid=107324667091065556014&rtpof=true&sd=true",
        "course": "47",
        "semester": "HK2",
        "year": "2025-2026"
    },
    {
        "fileName": "145-CLC47(TA).xlsx",
        "fileUrl": "https://docs.google.com/spreadsheets/d/1GFq7DoljvI1hEJLmTmhqy1gdXMZCDY7q/edit?usp=drivesdk&ouid=107324667091065556014&rtpof=true&sd=true",
        "course": "47",
        "semester": "HK2",
        "year": "2025-2026"
    },
    {
        "fileName": "148-LE47(B).xlsx",
        "fileUrl": "https://docs.google.com/spreadsheets/d/1IX9E0YpnzI_Mq_FMgPSGXVl_MV7VUHe3/edit?usp=drivesdk&ouid=107324667091065556014&rtpof=true&sd=true",
        "course": "47",
        "semester": "HK2",
        "year": "2025-2026"
    },
    {
        "fileName": "145-CLC47(F).xlsx",
        "fileUrl": "https://docs.google.com/spreadsheets/d/1LkSmF24OYhM_mK_ZAViEby-AzZG2WDyx/edit?usp=drivesdk&ouid=107324667091065556014&rtpof=true&sd=true",
        "course": "47",
        "semester": "HK2",
        "year": "2025-2026"
    },
    {
        "fileName": "145-CLC47(E).xlsx",
        "fileUrl": "https://docs.google.com/spreadsheets/d/1UHZC9YQa5LoK_9digpYY3SKBN7RY0tcA/edit?usp=drivesdk&ouid=107324667091065556014&rtpof=true&sd=true",
        "course": "47",
        "semester": "HK2",
        "year": "2025-2026"
    },
    {
        "fileName": "148-LE47(A).xlsx",
        "fileUrl": "https://docs.google.com/spreadsheets/d/1WLahx3oamXUcXIwI8Obgu-HXH9Yui8Yu/edit?usp=drivesdk&ouid=107324667091065556014&rtpof=true&sd=true",
        "course": "47",
        "semester": "HK2",
        "year": "2025-2026"
    },
    {
        "fileName": "149-Luật TMQT47.xlsx",
        "fileUrl": "https://docs.google.com/spreadsheets/d/1fhGmdDPePO8yrmmKb-4-tVE1Fr1z45dW/edit?usp=drivesdk&ouid=107324667091065556014&rtpof=true&sd=true",
        "course": "47",
        "semester": "HK2",
        "year": "2025-2026"
    },
    {
        "fileName": "145-CLC47(QTKD).xlsx",
        "fileUrl": "https://docs.google.com/spreadsheets/d/1jAFYSPZBR67mOU4x7nSKd3RHei779JFb/edit?usp=drivesdk&ouid=107324667091065556014&rtpof=true&sd=true",
        "course": "47",
        "semester": "HK2",
        "year": "2025-2026"
    },
    {
        "fileName": "145-CLC47QTL(B).xlsx",
        "fileUrl": "https://docs.google.com/spreadsheets/d/1vPd_Sz-5LXEKOUbZrA1jc9Mcaqzx6XUt/edit?usp=drivesdk&ouid=107324667091065556014&rtpof=true&sd=true",
        "course": "47",
        "semester": "HK2",
        "year": "2025-2026"
    },
    {
        "fileName": "145-CLC47QTL(A).xlsx",
        "fileUrl": "https://docs.google.com/spreadsheets/d/1wB7Auhvq-ZEPpTeIRaxVvcYbZXpuVUl6/edit?usp=drivesdk&ouid=107324667091065556014&rtpof=true&sd=true",
        "course": "47",
        "semester": "HK2",
        "year": "2025-2026"
    },
    {
        "fileName": "143-QTKD47(A).xlsx",
        "fileUrl": "https://docs.google.com/spreadsheets/d/15bNbiLO244YdNBAnpo8jSLiZts8EecMr/edit?usp=drivesdk&ouid=107324667091065556014&rtpof=true&sd=true",
        "course": "47",
        "semester": "HK2",
        "year": "2025-2026"
    },
    {
        "fileName": "138-TM47-nhom2.xlsx",
        "fileUrl": "https://docs.google.com/spreadsheets/d/1A55sMpQ7hKALnRQwuy9vt3ckTbrKXfEv/edit?usp=drivesdk&ouid=107324667091065556014&rtpof=true&sd=true",
        "course": "47",
        "semester": "HK2",
        "year": "2025-2026"
    },
    {
        "fileName": "140-QT47-nhom1.xlsx",
        "fileUrl": "https://docs.google.com/spreadsheets/d/1InG8HPep1N7NrBb1lO8igU9_9OFplxw1/edit?usp=drivesdk&ouid=107324667091065556014&rtpof=true&sd=true",
        "course": "47",
        "semester": "HK2",
        "year": "2025-2026"
    },
    {
        "fileName": "145-CLC47(A).xlsx",
        "fileUrl": "https://docs.google.com/spreadsheets/d/1Iz-qB_9kLRuBkpYmZAj-dBqLrOBth71L/edit?usp=drivesdk&ouid=107324667091065556014&rtpof=true&sd=true",
        "course": "47",
        "semester": "HK2",
        "year": "2025-2026"
    },
    {
        "fileName": "143-QTKD47(B).xlsx",
        "fileUrl": "https://docs.google.com/spreadsheets/d/1L1Ra45VWt1x81srIXVDaSbrm1Fyz-Oav/edit?usp=drivesdk&ouid=107324667091065556014&rtpof=true&sd=true",
        "course": "47",
        "semester": "HK2",
        "year": "2025-2026"
    },
    {
        "fileName": "145-CLC47(C).xlsx",
        "fileUrl": "https://docs.google.com/spreadsheets/d/1NOXGmYFtNL4eXCav_inzqlnVvv1xxZq8/edit?usp=drivesdk&ouid=107324667091065556014&rtpof=true&sd=true",
        "course": "47",
        "semester": "HK2",
        "year": "2025-2026"
    },
    {
        "fileName": "142-HC47-nhom4.xlsx",
        "fileUrl": "https://docs.google.com/spreadsheets/d/1TrjchRBHTyZ2TD7A8c7ScwNIO4JN13iA/edit?usp=drivesdk&ouid=107324667091065556014&rtpof=true&sd=true",
        "course": "47",
        "semester": "HK2",
        "year": "2025-2026"
    },
    {
        "fileName": "144-QTL47(B).xlsx",
        "fileUrl": "https://docs.google.com/spreadsheets/d/1TuiAPVY4x2fSz73-MjYtazgarOUafd_k/edit?usp=drivesdk&ouid=107324667091065556014&rtpof=true&sd=true",
        "course": "47",
        "semester": "HK2",
        "year": "2025-2026"
    },
    {
        "fileName": "142-HC47-nhom3.xlsx",
        "fileUrl": "https://docs.google.com/spreadsheets/d/1VtEpJeAW5y3W2gblvFkV4lPFMKziFehw/edit?usp=drivesdk&ouid=107324667091065556014&rtpof=true&sd=true",
        "course": "47",
        "semester": "HK2",
        "year": "2025-2026"
    },
    {
        "fileName": "139-DS47-nhom1.xlsx",
        "fileUrl": "https://docs.google.com/spreadsheets/d/1X2iLbpzTqfq4YS6678yxHvQwO63UnwFV/edit?usp=drivesdk&ouid=107324667091065556014&rtpof=true&sd=true",
        "course": "47",
        "semester": "HK2",
        "year": "2025-2026"
    },
    {
        "fileName": "139-DS47-nhom3.xlsx",
        "fileUrl": "https://docs.google.com/spreadsheets/d/1ZPxwO8-LQPWuGdJw9Ujh7zO6_jxAvgH2/edit?usp=drivesdk&ouid=107324667091065556014&rtpof=true&sd=true",
        "course": "47",
        "semester": "HK2",
        "year": "2025-2026"
    },
    {
        "fileName": "141-HS47(A).xlsx",
        "fileUrl": "https://docs.google.com/spreadsheets/d/1dMTs_Ex50vtbBisVWTmXi05w7FXWTwfu/edit?usp=drivesdk&ouid=107324667091065556014&rtpof=true&sd=true",
        "course": "47",
        "semester": "HK2",
        "year": "2025-2026"
    },
    {
        "fileName": "138-TM47-nhom3.xlsx",
        "fileUrl": "https://docs.google.com/spreadsheets/d/1g7YorZxypWTNWECk0D0-8VNWzNsHFiXI/edit?usp=drivesdk&ouid=107324667091065556014&rtpof=true&sd=true",
        "course": "47",
        "semester": "HK2",
        "year": "2025-2026"
    },
    {
        "fileName": "139-DS47-nhom2.xlsx",
        "fileUrl": "https://docs.google.com/spreadsheets/d/1gOgxPNFCViTBVikeRxqdI8L--rePiHtq/edit?usp=drivesdk&ouid=107324667091065556014&rtpof=true&sd=true",
        "course": "47",
        "semester": "HK2",
        "year": "2025-2026"
    },
    {
        "fileName": "145-CLC47(D).xlsx",
        "fileUrl": "https://docs.google.com/spreadsheets/d/1h83yVQf88gYMP9K0ossLgbPPv0-ifJ9o/edit?usp=drivesdk&ouid=107324667091065556014&rtpof=true&sd=true",
        "course": "47",
        "semester": "HK2",
        "year": "2025-2026"
    },
    {
        "fileName": "140-QT47-nhom3.xlsx",
        "fileUrl": "https://docs.google.com/spreadsheets/d/1i-wLYd-s-TCoRfb5CNfcbTmeoBWDIfFD/edit?usp=drivesdk&ouid=107324667091065556014&rtpof=true&sd=true",
        "course": "47",
        "semester": "HK2",
        "year": "2025-2026"
    },
    {
        "fileName": "140-QT47-nhom2.xlsx",
        "fileUrl": "https://docs.google.com/spreadsheets/d/1lOisozVqjSpCNnXxSRmr08B_UUKefLwO/edit?usp=drivesdk&ouid=107324667091065556014&rtpof=true&sd=true",
        "course": "47",
        "semester": "HK2",
        "year": "2025-2026"
    },
    {
        "fileName": "141-HS47(B).xlsx",
        "fileUrl": "https://docs.google.com/spreadsheets/d/1lokNu3dlfJhMQOc4M6Os7gZ0bwhCHhwI/edit?usp=drivesdk&ouid=107324667091065556014&rtpof=true&sd=true",
        "course": "47",
        "semester": "HK2",
        "year": "2025-2026"
    },
    {
        "fileName": "142-HC47-nhom1.xlsx",
        "fileUrl": "https://docs.google.com/spreadsheets/d/1nTdQfB4gYkAFCn2AZbxyr8tnfQABJ48F/edit?usp=drivesdk&ouid=107324667091065556014&rtpof=true&sd=true",
        "course": "47",
        "semester": "HK2",
        "year": "2025-2026"
    },
    {
        "fileName": "139-DS47-nhom4.xlsx",
        "fileUrl": "https://docs.google.com/spreadsheets/d/1nbJeo2-hiAflucaQpWhIls4ZxVWCbSqm/edit?usp=drivesdk&ouid=107324667091065556014&rtpof=true&sd=true",
        "course": "47",
        "semester": "HK2",
        "year": "2025-2026"
    },
    {
        "fileName": "142-HC47-nhom2.xlsx",
        "fileUrl": "https://docs.google.com/spreadsheets/d/1plkFlawGzscUSN4k8PhEyoBbx7eVtIPY/edit?usp=drivesdk&ouid=107324667091065556014&rtpof=true&sd=true",
        "course": "47",
        "semester": "HK2",
        "year": "2025-2026"
    },
    {
        "fileName": "138-TM47-nhom4.xlsx",
        "fileUrl": "https://docs.google.com/spreadsheets/d/1qrK9qNnT-9PDCyjLCVm_-DULZdf-wpDR/edit?usp=drivesdk&ouid=107324667091065556014&rtpof=true&sd=true",
        "course": "47",
        "semester": "HK2",
        "year": "2025-2026"
    },
    {
        "fileName": "140-QT47-nhom4.xlsx",
        "fileUrl": "https://docs.google.com/spreadsheets/d/1rFQGaiNmby-pQcrfhpj9TMNY8rGFe_4F/edit?usp=drivesdk&ouid=107324667091065556014&rtpof=true&sd=true",
        "course": "47",
        "semester": "HK2",
        "year": "2025-2026"
    },
    {
        "fileName": "144-QTL47(A).xlsx",
        "fileUrl": "https://docs.google.com/spreadsheets/d/1xCypQxq2EBwBSUKJzQoFPJ5V3Kx69Xgm/edit?usp=drivesdk&ouid=107324667091065556014&rtpof=true&sd=true",
        "course": "47",
        "semester": "HK2",
        "year": "2025-2026"
    },
    {
        "fileName": "145-CLC47(B).xlsx",
        "fileUrl": "https://docs.google.com/spreadsheets/d/1yPssClnLYzMmWl9Bx-gVX8cH3gUyrOc1/edit?usp=drivesdk&ouid=107324667091065556014&rtpof=true&sd=true",
        "course": "47",
        "semester": "HK2",
        "year": "2025-2026"
    },
    {
        "fileName": "138-TM47-nhom1.xlsx",
        "fileUrl": "https://docs.google.com/spreadsheets/d/1zkoLBvwlUpMANHgRk5AvHwmtWkqlm2wN/edit?usp=drivesdk&ouid=107324667091065556014&rtpof=true&sd=true",
        "course": "47",
        "semester": "HK2",
        "year": "2025-2026"
    }
]